mercariscanner/__init__.py
mercariscanner/__main__.py
mercariscanner/mercari_scanner.py
mercariscanner/mercari_spider.py
mercariscanner/alerters/alerter.py
mercariscanner/alerters/slack.py
mercari_scanner-0.2.0.dist-info/LICENSE
mercari_scanner-0.2.0.dist-info/METADATA
mercari_scanner-0.2.0.dist-info/WHEEL
mercari_scanner-0.2.0.dist-info/top_level.txt
mercari_scanner-0.2.0.dist-info/RECORD
