Metadata-Version: 2.1
Name: mercari-scanner
Version: 0.2.0
Summary: Scan and receive alerts for newly listed items on Mercari
Author-email: Chad Bowman <chad.bowman0+github@gmail.com>
Project-URL: Homepage, https://github.com/ChadBowman/mercari-scanner
Classifier: Programming Language :: Python :: 3
Classifier: License :: OSI Approved :: MIT License
Requires-Python: >=3.9
License-File: LICENSE
Requires-Dist: requests (>=2.25.1)
Requires-Dist: scrapy (>=2.4.1)
